bmdf/__init__.py
bmdf/utils.py
bmdf/cli/__init__.py
bmdf-0.6.2.dist-info/licenses/LICENSE
mdcmd/__init__.py
mdcmd/cli/__init__.py
mktoc/__init__.py
mktoc/cli/__init__.py
bmdf-0.6.2.dist-info/METADATA
bmdf-0.6.2.dist-info/WHEEL
bmdf-0.6.2.dist-info/entry_points.txt
bmdf-0.6.2.dist-info/top_level.txt
bmdf-0.6.2.dist-info/RECORD
