Metadata-Version: 2.4
Name: bmdf
Version: 0.6.2
Summary: Execute commands in Markdown files, embed output, generate TOCs
Author-email: Ryan Williams <ryan@runsascoded.com>
License: MIT
Project-URL: Homepage, https://github.com/runsascoded/bash-markdown-fence
Project-URL: Repository, https://github.com/runsascoded/bash-markdown-fence.git
Project-URL: Bug Tracker, https://github.com/runsascoded/bash-markdown-fence/issues
Requires-Python: >=3.10
License-File: LICENSE
Requires-Dist: utz>=0.19.1
Requires-Dist: click>=8
Provides-Extra: test
Requires-Dist: pytest; extra == "test"
Dynamic: license-file
